Workbook

Sheet Instrucciones
A1: Proyecto de práctica: Estructura de precios y rentabilidad
A3: Este archivo es para que practiques el análisis de precios de una tienda de conveniencia
A4: dentro de una gasolinera, tal como lo haría un Analista de Precios.
A6: Ve a la hoja 'Datos'. Ahí encontrarás 15 productos con: Producto, Categoría, Costo unitario,
A7: Precio de venta, Unidades vendidas al mes y Costo fijo asignado al mes.
A9: Las columnas resaltadas en AMARILLO están vacías. Tu trabajo es escribir la fórmula
A10: correspondiente en la PRIMERA fila de cada columna vacía, y luego copiarla hacia abajo
A11: para las 15 filas (seleccioná la celda, doble clic en la esquina inferior derecha, o
A12: copiar y pegar en el resto de filas).
A14: Guía de qué calcular en cada columna (sin darte la fórmula exacta, para que la construyas tú):
A16: G - Utilidad unitaria: cuánto ganás en Lempiras por cada unidad vendida.
A17: H - Margen (%): la utilidad unitaria como porcentaje del PRECIO DE VENTA.
... A27: Tip: si una fórmula te da #DIV/0!, revisá que no estés dividiendo entre una celda en cero.

Sheet Hoja1
A3: Etiquetas de fila | B3: Suma de Utilidad neta total (L.) | C3: Promedio de Margen (%)
A4: Automotriz | B4: 3050 | C4: 0.36842105
A5: Bebidas | B5: 16900 | C5: 0.46496544
A6: Bebidas calientes | B6: 12400 | C6: 0.68928571
A7: Combustible | B7: 75000 | C7: 0.11453634
A8: Comida rápida | B8: 5200 | C8: 0.46875
A9: Otros | B9: 1420 | C9: 0.5
A10: Snacks | B10: 11700 | C10: 0.47175926
A11: Tabaco | B11: 3670 | C11: 0.25
A12: Total general | B12: 129340 | C12: 0.43158262

Sheet Resumen_Categoría
A1: Categoría | B1: Utilidad neta por cat | C1: Elasticidad asumida
A2: Bebidas | B2: =SUMIF(Productos!B2:B16,A2,Productos!M2:M16) -> 16900 | C2: -1.2 | D2: Medio | E2: =COUNTIF(Productos!N2:N16,D2) -> 8
A3: Bebidas calientes | B3: =SUMIF(Productos!B3:B16,A3,Productos!M3:M16) -> 12400 | C3: -0.8 | D3: Alto | E3: =COUNTIF(Productos!N3:N16,D3) -> 5
A4: Snacks | B4: =SUMIF(Productos!B4:B17,A4,Productos!M4:M17) -> 11700 | C4: -1.5 | D4: Bajo | E4: =COUNTIF(Productos!N4:N17,D4) -> 2
A5: Comida rápida | B5: =SUMIF(Productos!B5:B18,A5,Productos!M5:M18) -> 5200 | C5: -1.3
A6: Tabaco | B6: =SUMIF(Productos!B6:B19,A6,Productos!M6:M19) -> 3670 | C6: -0.3
A7: Otros | B7: =SUMIF(Productos!B7:B20,A7,Productos!M7:M20) -> 1420 | C7: -1
A8: Automotriz | B8: =SUMIF(Productos!B8:B21,A8,Productos!M8:M21) -> 3050 | C8: -0.5
A9: Combustible | B9: =SUMIF(Productos!B9:B22,A9,Productos!M9:M22) -> 75000 | C9: -0.2

Sheet Productos
A1: Producto | B1: Categoría | C1: Costo unitario (L.) | D1: Precio venta (L.) | E1: Unidades vendidas/mes | F1: Costo fijo asignado/mes (L.) | G1: Utilidad unitaria (L.) | H1: Margen (%) | I1: Markup (%) | J1: Ingreso total (L.) | K1: Costo variable total (L.) | L1: Utilidad bruta total (L.) | M1: Utilidad neta total (L.) | N1: Clasificación | O1: Control | P1: Precio simulado | Q1: Margen simulado | R1: Elasticidad asumida | S1: Unidades simuladas
A2: Agua 600ml | B2: Bebidas | C2: 8 | D2: 15 | E2: 800 | F2: 200 | G2: =D2-C2 -> 7 | H2: =(D2-C2)/D2 -> 0.46666667 | I2: =(D2-C2)/C2 -> 0.875 | J2: =D2*E2 -> 12000 | K2: =C2*E2 -> 6400 | L2: =J2-K2 -> 5600 | M2: =L2-F2 -> 5400 | N2: =IF(ROUND(H2,4)>=0.5,"Alto",IF(ROUND(H2,4)>=0.25,"Medio","Bajo")) -> Medio | O2: 0.1 | P2: =D2+(D2*$O$2) -> 16.5 | Q2: =(P2-C2)/P2 -> 0.51515152 | R2: =_xlfn.XLOOKUP(B2,Resumen_Categoría!$A$2:$A$9,Resumen_Categoría!$C$2:$C$9) -> -1.2 | S2: =E2*(1+R2*$O$2) -> 704
A3: Gaseosa 500ml | B3: Bebidas | C3: 12 | D3: 22 | E3: 650 | F3: 200 | G3: =D3-C3 -> 10 | H3: =(D3-C3)/D3 -> 0.45454545 | I3: =(D3-C3)/C3 -> 0.83333333 | J3: =D3*E3 -> 14300 | K3: =C3*E3 -> 7800 | L3: =J3-K3 -> 6500 | M3: =L3-F3 -> 6300 | N3: =IF(ROUND(H3,4)>=0.5,"Alto",IF(ROUND(H3,4)>=0.25,"Medio","Bajo")) -> Medio | O3: 0.1 | P3: =D3+(D3*$O$2) -> 24.2 | Q3: =(P3-C3)/P3 -> 0.50413223 | R3: =_xlfn.XLOOKUP(B3,Resumen_Categoría!$A$2:$A$9,Resumen_Categoría!$C$2:$C$9) -> -1.2 | S3: =E3*(1+R3*$O$2) -> 572
A4: Energizante | B4: Bebidas | C4: 20 | D4: 38 | E4: 300 | F4: 200 | G4: =D4-C4 -> 18 | H4: =(D4-C4)/D4 -> 0.47368421 | I4: =(D4-C4)/C4 -> 0.9 | J4: =D4*E4 -> 11400 | K4: =C4*E4 -> 6000 | L4: =J4-K4 -> 5400 | M4: =L4-F4 -> 5200 | N4: =IF(ROUND(H4,4)>=0.5,"Alto",IF(ROUND(H4,4)>=0.25,"Medio","Bajo")) -> Medio | O4: 0.1 | P4: =D4+(D4*$O$2) -> 41.8 | Q4: =(P4-C4)/P4 -> 0.5215311 | R4: =_xlfn.XLOOKUP(B4,Resumen_Categoría!$A$2:$A$9,Resumen_Categoría!$C$2:$C$9) -> -1.2 | S4: =E4*(1+R4*$O$2) -> 264
A5: Café pequeño | B5: Bebidas calientes | C5: 6 | D5: 20 | E5: 500 | F5: 150 | G5: =D5-C5 -> 14 | H5: =(D5-C5)/D5 -> 0.7 | I5: =(D5-C5)/C5 -> 2.3333333 | J5: =D5*E5 -> 10000 | K5: =C5*E5 -> 3000 | L5: =J5-K5 -> 7000 | M5: =L5-F5 -> 6850 | N5: =IF(ROUND(H5,4)>=0.5,"Alto",IF(ROUND(H5,4)>=0.25,"Medio","Bajo")) -> Alto | O5: 0.1 | P5: =D5+(D5*$O$2) -> 22 | Q5: =(P5-C5)/P5 -> 0.72727273 | R5: =_xlfn.XLOOKUP(B5,Resumen_Categoría!$A$2:$A$9,Resumen_Categoría!$C$2:$C$9) -> -0.8 | S5: =E5*(1+R5*$O$2) -> 460
A6: Café grande | B6: Bebidas calientes | C6: 9 | D6: 28 | E6: 300 | F6: 150 | G6: =D6-C6 -> 19 | H6: =(D6-C6)/D6 -> 0.67857143 | I6: =(D6-C6)/C6 -> 2.1111111 | J6: =D6*E6 -> 8400 | K6: =C6*E6 -> 2700 | L6: =J6-K6 -> 5700 | M6: =L6-F6 -> 5550 | N6: =IF(ROUND(H6,4)>=0.5,"Alto",IF(ROUND(H6,4)>=0.25,"Medio","Bajo")) -> Alto | O6: 0.1 | P6: =D6+(D6*$O$2) -> 30.8 | Q6: =(P6-C6)/P6 -> 0.70779221 | R6: =_xlfn.XLOOKUP(B6,Resumen_Categoría!$A$2:$A$9,Resumen_Categoría!$C$2:$C$9) -> -0.8 | S6: =E6*(1+R6*$O$2) -> 276
A7: Snack papas | B7: Snacks | C7: 10 | D7: 18 | E7: 600 | F7: 100 | G7: =D7-C7 -> 8 | H7: =(D7-C7)/D7 -> 0.44444444 | I7: =(D7-C7)/C7 -> 0.8 | J7: =D7*E7 -> 10800 | K7: =C7*E7 -> 6000 | L7: =J7-K7 -> 4800 | M7: =L7-F7 -> 4700 | N7: =IF(ROUND(H7,4)>=0.5,"Alto",IF(ROUND(H7,4)>=0.25,"Medio","Bajo")) -> Medio | O7: 0.1 | P7: =D7+(D7*$O$2) -> 19.8 | Q7: =(P7-C7)/P7 -> 0.49494949 | R7: =_xlfn.XLOOKUP(B7,Resumen_Categoría!$A$2:$A$9,Resumen_Categoría!$C$2:$C$9) -> -1.5 | S7: =E7*(1+R7*$O$2) -> 510
A8: Chocolate barra | B8: Snacks | C8: 7 | D8: 15 | E8: 550 | F8: 100 | G8: =D8-C8 -> 8 | H8: =(D8-C8)/D8 -> 0.53333333 | I8: =(D8-C8)/C8 -> 1.1428571 | J8: =D8*E8 -> 8250 | K8: =C8*E8 -> 3850 | L8: =J8-K8 -> 4400 | M8: =L8-F8 -> 4300 | N8: =IF(ROUND(H8,4)>=0.5,"Alto",IF(ROUND(H8,4)>=0.25,"Medio","Bajo")) -> Alto | O8: 0.1 | P8: =D8+(D8*$O$2) -> 16.5 | Q8: =(P8-C8)/P8 -> 0.57575758 | R8: =_xlfn.XLOOKUP(B8,Resumen_Categoría!$A$2:$A$9,Resumen_Categoría!$C$2:$C$9) -> -1.5 | S8: =E8*(1+R8*$O$2) -> 467.5
A9: Galletas paquete | B9: Snacks | C9: 9 | D9: 16 | E9: 400 | F9: 100 | G9: =D9-C9 -> 7 | H9: =(D9-C9)/D9 -> 0.4375 | I9: =(D9-C9)/C9 -> 0.77777778 | J9: =D9*E9 -> 6400 | K9: =C9*E9 -> 3600 | L9: =J9-K9 -> 2800 | M9: =L9-F9 -> 2700 | N9: =IF(ROUND(H9,4)>=0.5,"Alto",IF(ROUND(H9,4)>=0.25,"Medio","Bajo")) -> Medio | O9: 0.1 | P9: =D9+(D9*$O$2) -> 17.6 | Q9: =(P9-C9)/P9 -> 0.48863636 | R9: =_xlfn.XLOOKUP(B9,Resumen_Categoría!$A$2:$A$9,Resumen_Categoría!$C$2:$C$9) -> -1.5 | S9: =E9*(1+R9*$O$2) -> 340
A10: Sándwich empacado | B10: Comida rápida | C10: 18 | D10: 32 | E10: 200 | F10: 150 | G10: =D10-C10 -> 14 | H10: =(D10-C10)/D10 -> 0.4375 | I10: =(D10-C10)/C10 -> 0.77777778 | J10: =D10*E10 -> 6400 | K10: =C10*E10 -> 3600 | L10: =J10-K10 -> 2800 | M10: =L10-F10 -> 2650 | N10: =IF(ROUND(H10,4)>=0.5,"Alto",IF(ROUND(H10,4)>=0.25,"Medio","Bajo")) -> Medio | O10: 0.1 | P10: =D10+(D10*$O$2) -> 35.2 | Q10: =(P10-C10)/P10 -> 0.48863636 | R10: =_xlfn.XLOOKUP(B10,Resumen_Categoría!$A$2:$A$9,Resumen_Categoría!$C$2:$C$9) -> -1.3 | S10: =E10*(1+R10*$O$2) -> 174
A11: Hot dog | B11: Comida rápida | C11: 15 | D11: 30 | E11: 180 | F11: 150 | G11: =D11-C11 -> 15 | H11: =(D11-C11)/D11 -> 0.5 | I11: =(D11-C11)/C11 -> 1 | J11: =D11*E11 -> 5400 | K11: =C11*E11 -> 2700 | L11: =J11-K11 -> 2700 | M11: =L11-F11 -> 2550 | N11: =IF(ROUND(H11,4)>=0.5,"Alto",IF(ROUND(H11,4)>=0.25,"Medio","Bajo")) -> Alto | O11: 0.1 | P11: =D11+(D11*$O$2) -> 33 | Q11: =(P11-C11)/P11 -> 0.54545455 | R11: =_xlfn.XLOOKUP(B11,Resumen_Categoría!$A$2:$A$9,Resumen_Categoría!$C$2:$C$9) -> -1.3 | S11: =E11*(1+R11*$O$2) -> 156.6
A12: Cigarros (paquete) | B12: Tabaco | C12: 45 | D12: 60 | E12: 250 | F12: 80 | G12: =D12-C12 -> 15 | H12: =(D12-C12)/D12 -> 0.25 | I12: =(D12-C12)/C12 -> 0.33333333 | J12: =D12*E12 -> 15000 | K12: =C12*E12 -> 11250 | L12: =J12-K12 -> 3750 | M12: =L12-F12 -> 3670 | N12: =IF(ROUND(H12,4)>=0.5,"Alto",IF(ROUND(H12,4)>=0.25,"Medio","Bajo")) -> Medio | O12: 0.1 | P12: =D12+(D12*$O$2) -> 66 | Q12: =(P12-C12)/P12 -> 0.31818182 | R12: =_xlfn.XLOOKUP(B12,Resumen_Categoría!$A$2:$A$9,Resumen_Categoría!$C$2:$C$9) -> -0.3 | S12: =E12*(1+R12*$O$2) -> 242.5
A13: Hielo bolsa | B13: Otros | C13: 10 | D13: 20 | E13: 150 | F13: 80 | G13: =D13-C13 -> 10 | H13: =(D13-C13)/D13 -> 0.5 | I13: =(D13-C13)/C13 -> 1 | J13: =D13*E13 -> 3000 | K13: =C13*E13 -> 1500 | L13: =J13-K13 -> 1500 | M13: =L13-F13 -> 1420 | N13: =IF(ROUND(H13,4)>=0.5,"Alto",IF(ROUND(H13,4)>=0.25,"Medio","Bajo")) -> Alto | O13: 0.1 | P13: =D13+(D13*$O$2) -> 22 | Q13: =(P13-C13)/P13 -> 0.54545455 | R13: =_xlfn.XLOOKUP(B13,Resumen_Categoría!$A$2:$A$9,Resumen_Categoría!$C$2:$C$9) -> -1 | S13: =E13*(1+R13*$O$2) -> 135
... A16: Combustible Premium (galón) | B16: Combustible | C16: 92 | D16: 105 | E16: 2000 | F16: 500 | G16: =D16-C16 -> 13 | H16: =(D16-C16)/D16 -> 0.12380952 | I16: =(D16-C16)/C16 -> 0.14130435 | J16: =D16*E16 -> 210000 | K16: =C16*E16 -> 184000 | L16: =J16-K16 -> 26000 | M16: =L16-F16 -> 25500 | N16: =IF(ROUND(H16,4)>=0.5,"Alto",IF(ROUND(H16,4)>=0.25,"Medio","Bajo")) -> Bajo | O16: 0.1 | P16: =D16+(D16*$O$2) -> 115.5 | Q16: =(P16-C16)/P16 -> 0.2034632 | R16: =_xlfn.XLOOKUP(B16,Resumen_Categoría!$A$2:$A$9,Resumen_Categoría!$C$2:$C$9) -> -0.2 | S16: =E16*(1+R16*$O$2) -> 1960

Sheet Resumen
A1: Resumen — Preguntas de negocio
A3: Pregunta | B3: Tu respuesta / fórmula
A4: Producto con MAYOR margen (%) | B4: =_xlfn.XLOOKUP(MAX(Productos!H2:H16),Productos!H2:H16,Productos!A2:A16) -> Café pequeño
A5: Producto con MAYOR utilidad neta total (L.) | B5: =_xlfn.XLOOKUP(MAX(Productos!M2:M16),Productos!M2:M16,Productos!A2:A16) -> Combustible Regular (galón)
A6: Producto con MENOR utilidad neta total (L.) | B6: =_xlfn.XLOOKUP(MIN(Productos!M2:M16),Productos!M2:M16,Productos!A2:A16) -> Hielo bolsa
A7: Categoría con mayor utilidad neta total (L.) | B7: =_xlfn.XLOOKUP(MAX(Resumen_Categoría!B2:B8),Resumen_Categoría!B2:B8,Resumen_Categoría!A2:A8) -> Bebidas
A8: ¿Coincide el producto de mayor margen con el de mayor utilidad? (Sí/No) | B8: No
A10: Tip: usá MAX, MIN, INDICE+COINCIDIR o BUSCARX, y SUMAR.SI para las categorías.
A13: Punto de equilibrio en unidades = Costo fijo asignado/ (Precio - Costo Unitario)
A15: Donde precio . Costo unitario = se conoce como margen de contribución por unidad. Que es, cuanto aporta cada unidad vendida para cubrir los costos fijos, antes de empezar a generar ganancia real.
A16: Un incremento en precios tiene mayor impacto en los mrgenes de ganancia cuando el margen de partida es bajo, si el margen es alto el efecto será menor, si todo lo demás permanece constante.
